Metadata-Version: 2.1
Name: nbclear
Version: 0.1.0
Summary: A tool to automatically remove the outputs from Jupyter notebooks.
Home-page: https://github.com/ozen/nbclear
Author: Yigit Ozen
Author-email: yigit@ozen.dev
License: MIT
Platform: UNKNOWN
Classifier: License :: OSI Approved :: MIT License
Classifier: Programming Language :: Python :: 3
Classifier: Programming Language :: Python :: 3 :: Only
Classifier: Programming Language :: Python :: 3.6
Classifier: Programming Language :: Python :: 3.7
Classifier: Programming Language :: Python :: 3.8
Classifier: Programming Language :: Python :: 3.9
Classifier: Programming Language :: Python :: 3.10
Classifier: Programming Language :: Python :: Implementation :: CPython
Requires-Python: >=3.6.1
